EmojiCrypt_pip/EmojiCrypt.py
EmojiCrypt_pip/__init__.py
EmojiCrypt_pip-1.7.dist-info/LICENSE.txt
EmojiCrypt_pip-1.7.dist-info/METADATA
EmojiCrypt_pip-1.7.dist-info/WHEEL
EmojiCrypt_pip-1.7.dist-info/top_level.txt
EmojiCrypt_pip-1.7.dist-info/RECORD
