Metadata-Version: 2.1
Name: EmojiCrypt_pip
Version: 1.7
Summary: encrypt text in emojis
Home-page: https://github.com/Nichokas
Download-URL: https://github.com/Nichokas/EmojiCrypt_pip
Author: Nichokas
Author-email: nicolas.rodalv@educa.jcyl.es
License: GNU v3
Classifier: Development Status :: 5 - Production/Stable
Classifier: Intended Audience :: Developers
Classifier: License :: OSI Approved :: GNU General Public License v3 or later (GPLv3+)
Classifier: Programming Language :: Python :: 3
Classifier: Programming Language :: Python :: 3.6
Classifier: Programming Language :: Python :: 3.7
Classifier: Programming Language :: Python :: 3.8
Classifier: Programming Language :: Python :: 3.9
License-File: LICENSE.txt
